dznpy/__init__.py
dznpy/ast.py
dznpy/ast_cpp_view.py
dznpy/ast_view.py
dznpy/cpp_gen.py
dznpy/cpp_gen_rule_of_five.py
dznpy/dzn_exe.py
dznpy/json_ast.py
dznpy/misc_utils.py
dznpy/scoping.py
dznpy/text_gen.py
dznpy/versioning.py
dznpy/adv_shell/__init__.py
dznpy/adv_shell/common.py
dznpy/adv_shell/port_selection.py
dznpy/adv_shell/types.py
dznpy/adv_shell/core/__init__.py
dznpy/adv_shell/core/processing.py
dznpy/support_files/__init__.py
dznpy/support_files/ilog.py
dznpy/support_files/meta_helpers.py
dznpy/support_files/misc_utils.py
dznpy/support_files/multi_client_selector.py
dznpy/support_files/mutex_wrapped.py
dznpy/support_files/strict_port.py
dznpy-1.3.0.dist-info/licenses/LICENSE
dznpy-1.3.0.dist-info/METADATA
dznpy-1.3.0.dist-info/WHEEL
dznpy-1.3.0.dist-info/top_level.txt
dznpy-1.3.0.dist-info/RECORD
