Metadata-Version: 2.4
Name: dznpy
Version: 1.3.0
Summary: Python modules to support in developing C++ software with Dezyne
Author-email: Michael van de Ven <michael@ftr-ict.com>
License-Expression: MIT
Project-URL: Homepage, https://github.com/mikeftrict/dznpy
Requires-Python: >=3.10
License-File: LICENSE
Requires-Dist: orjson>=3.8
Requires-Dist: typing_extensions>=4.4
Provides-Extra: dev
Requires-Dist: pytest>=7.1; extra == "dev"
Requires-Dist: pytest-cov; extra == "dev"
Requires-Dist: pylint>=2.17.1; extra == "dev"
Requires-Dist: flake8>=6.0.0; extra == "dev"
Dynamic: license-file
